MANIFEST.in
README.rst
requirements.txt
setup.cfg
setup.py
django_msp_facturaglobal/__init__.py
django_msp_facturaglobal/__init__.pyc
django_msp_facturaglobal/config.pyc
django_msp_facturaglobal/forms.pyc
django_msp_facturaglobal/models.pyc
django_msp_facturaglobal/test_facturas.py
django_msp_facturaglobal/test_facturas.pyc
django_msp_facturaglobal/tests.py
django_msp_facturaglobal/tests.pyc
django_msp_facturaglobal/urls.pyc
django_msp_facturaglobal/views.pyc
django_msp_facturaglobal.egg-info/PKG-INFO
django_msp_facturaglobal.egg-info/SOURCES.txt
django_msp_facturaglobal.egg-info/dependency_links.txt
django_msp_facturaglobal.egg-info/requires.txt
django_msp_facturaglobal.egg-info/top_level.txt
django_msp_facturaglobal/static/django_msp_facturaglobal/js/documentos.factura.js
django_msp_facturaglobal/static/django_msp_facturaglobal/js/jquery.articulosearch.js
django_msp_facturaglobal/static/images/ui-anim_basic_16x16.gif
django_msp_facturaglobal/templates/django_msp_facturaglobal/base.html
django_msp_facturaglobal/templates/django_msp_facturaglobal/index.html
django_msp_facturaglobal/templates/django_msp_facturaglobal/facturas/factura.html
django_msp_facturaglobal/templates/django_msp_facturaglobal/facturas/factura_global.html
django_msp_facturaglobal/templates/django_msp_facturaglobal/facturas/facturas.html